<?xml version="1.0" encoding="UTF-8" standalone="no"?>
<root>

	<de>
		<title>Apfelkuchen</title>

		<mnuHelp>Help</mnuHelp>
		<mnuItemAbout>About</mnuItemAbout>

		<buttonNext>Optimieren</buttonNext>
		<buttonOk>
			OK
		</buttonOk>

		<buttonOkStart>
			Start
		</buttonOkStart>
		<nameLabel>
			Name für das Feld
		</nameLabel>
		<labelName>
			Name
		</labelName>
		<labelAbbr>
			Abkürzung
		</labelAbbr>
		
		<buttonNewField>
			Neuer Faktor
		</buttonNewField>
		<buttonRemove>
			Faktor Löschen
		</buttonRemove>
		<buttonNewStart>
			Neu Starten
		</buttonNewStart>
		<experimentLabel>Versuch </experimentLabel>
		<buttonOKTipText>Hovered Over ME Test</buttonOKTipText>
		<buttonNextTipText>Bestätigen die Eingaben</buttonNextTipText>
		<errorSelection>Bitte wählen Sie eine Variante aus</errorSelection>
		<labelRole>Rolle</labelRole>
		<labelDimension> Dimension</labelDimension>
		<labelUnit>Einheit</labelUnit>
		<labelLow>Min</labelLow>
		<labelHigh>Max</labelHigh>
		<labelSIMin>Si-Min</labelSIMin>
		<labelSIMax>Si-Max</labelSIMax>


		<errorTitleDialog>Fehler</errorTitleDialog>
		<errorTextDialog>Bitte prüfen Sie eingaben</errorTextDialog>
	</de>

</root>